apiserver/README.md
apiserver/__init__.py
apiserver/api_server.py
apiserver/message_manager.py
apiserver/prompt_logger.py
apiserver/start_server.py
apiserver/streaming_tool_extractor.py
apiserver/tool_call_utils.py
apiserver/static/document_upload.html
mcpserver/agent_manager.py
mcpserver/agent_manager_README.md
mcpserver/mcp_manager.py
mcpserver/mcp_registry.py
mcpserver/tool_call_utils.py
mcpserver/Office-Word-MCP-Server-main/.gitignore
mcpserver/Office-Word-MCP-Server-main/DOCUMENT_INTEGRATION_SUMMARY.md
mcpserver/Office-Word-MCP-Server-main/Dockerfile
mcpserver/Office-Word-MCP-Server-main/LICENSE
mcpserver/Office-Word-MCP-Server-main/NAGA文档处理功能技术文档.md
mcpserver/Office-Word-MCP-Server-main/__init__.py
mcpserver/Office-Word-MCP-Server-main/agent-manifest.json
mcpserver/Office-Word-MCP-Server-main/mcp-config.json
mcpserver/Office-Word-MCP-Server-main/pyproject.toml
mcpserver/Office-Word-MCP-Server-main/requirements.txt
mcpserver/Office-Word-MCP-Server-main/setup_mcp.py
mcpserver/Office-Word-MCP-Server-main/smithery.yaml
mcpserver/Office-Word-MCP-Server-main/word_mcp_adapter.py
mcpserver/Office-Word-MCP-Server-main/word_mcp_server.py
mcpserver/Office-Word-MCP-Server-main/office_word_mcp_server/__init__.py
mcpserver/Office-Word-MCP-Server-main/word_document_server/__init__.py
mcpserver/Office-Word-MCP-Server-main/word_document_server/main.py
mcpserver/Office-Word-MCP-Server-main/word_document_server/core/__init__.py
mcpserver/Office-Word-MCP-Server-main/word_document_server/core/footnotes.py
mcpserver/Office-Word-MCP-Server-main/word_document_server/core/protection.py
mcpserver/Office-Word-MCP-Server-main/word_document_server/core/styles.py
mcpserver/Office-Word-MCP-Server-main/word_document_server/core/tables.py
mcpserver/Office-Word-MCP-Server-main/word_document_server/core/unprotect.py
mcpserver/Office-Word-MCP-Server-main/word_document_server/tools/__init__.py
mcpserver/Office-Word-MCP-Server-main/word_document_server/tools/content_tools.py
mseep_nagaagent-3.1.1.dist-info/METADATA
mseep_nagaagent-3.1.1.dist-info/WHEEL
mseep_nagaagent-3.1.1.dist-info/entry_points.txt
mseep_nagaagent-3.1.1.dist-info/licenses/LICENSE
mseep_nagaagent-3.1.1.dist-info/RECORD
