Metadata-Version: 2.4
Name: mseep-nagaagent
Version: 3.1.1
Summary: NagaAgent 3.1 - 智能对话助手，支持多MCP服务、流式语音交互、GRAG知识图谱记忆系统、RESTful API接口、控制台托盘功能
Author-email: mseep <support@skydeck.ai>
License-File: LICENSE
Requires-Python: >=3.10
Requires-Dist: aiohttp>=3.11.18
Requires-Dist: anyio>=4.9.0
Requires-Dist: bottleneck>=1.3.6
Requires-Dist: certifi>=2025.4.26
Requires-Dist: charset-normalizer>=3.4.1
Requires-Dist: colorama>=0.4.6
Requires-Dist: comtypes
Requires-Dist: crawl4ai>=0.7.4
Requires-Dist: edge-tts>=7.0.2
Requires-Dist: emoji>=2.8.0
Requires-Dist: fastapi>=0.115.0
Requires-Dist: fastmcp>=2.11.2
Requires-Dist: flask-cors>=6.0.1
Requires-Dist: flask>=3.1.0
Requires-Dist: gevent>=25.5.1
Requires-Dist: greenlet>=3.2.1
Requires-Dist: griffe>=1.7.3
Requires-Dist: html2text>=2020.1.16
Requires-Dist: httpx-sse>=0.4.0
Requires-Dist: httpx>=0.28.1
Requires-Dist: idna>=3.10
Requires-Dist: jmcomic>=2.6.5
Requires-Dist: langchain-community>=0.3.21
Requires-Dist: langchain>=0.3.27
Requires-Dist: librosa
Requires-Dist: markdown>=3.8
Requires-Dist: matplotlib>=3.10.0
Requires-Dist: mcp>=1.6.0
Requires-Dist: mqtt-tool>=0.1.1
Requires-Dist: numpy<2.0.0,>=1.24.0
Requires-Dist: onnxruntime>=1.22.1
Requires-Dist: openai-agents>=0.0.13
Requires-Dist: openai>=1.76.0
Requires-Dist: paho-mqtt>=2.0.0
Requires-Dist: pandas<3.0.0,>=2.0.0
Requires-Dist: pillow>=10.0.0
Requires-Dist: playwright>=1.52.0
Requires-Dist: py2neo>=2021.2.3
Requires-Dist: pyaudio>=0.2.14
Requires-Dist: pycaw
Requires-Dist: pydantic-settings>=2.9.1
Requires-Dist: pydantic>=2.11.3
Requires-Dist: pyee>=13.0.0
Requires-Dist: pygame>=2.6.0
Requires-Dist: pyqt5-qt5==5.15.2
Requires-Dist: pyqt5==5.15.11
Requires-Dist: pystray>=0.19.4
Requires-Dist: python-dateutil>=2.9.0.post0
Requires-Dist: python-docx>=1.2.0
Requires-Dist: python-dotenv>=1.1.0
Requires-Dist: pytz>=2024.1
Requires-Dist: pyvis>=0.3.2
Requires-Dist: requests>=2.32.3
Requires-Dist: scikit-learn>=1.6.1
Requires-Dist: scipy>=1.15.2
Requires-Dist: screen-brightness-control
Requires-Dist: sounddevice>=0.4.6
Requires-Dist: soundfile>=0.12.1
Requires-Dist: sse-starlette>=2.3.3
Requires-Dist: starlette>=0.46.2
Requires-Dist: tiktoken
Requires-Dist: tqdm>=4.67.1
Requires-Dist: transformers>=4.51.3
Requires-Dist: typing-extensions>=4.13.2
Requires-Dist: urllib3>=2.4.0
Requires-Dist: uvicorn[standard]>=0.34.0
Requires-Dist: websockets>=14.0
Provides-Extra: audio
Requires-Dist: pyaudio>=0.2.14; extra == 'audio'
Requires-Dist: sounddevice>=0.4.6; extra == 'audio'
Requires-Dist: soundfile>=0.12.1; extra == 'audio'
Provides-Extra: dev
Requires-Dist: black>=22.0.0; extra == 'dev'
Requires-Dist: pytest-asyncio>=0.20.0; extra == 'dev'
Requires-Dist: pytest>=7.0.0; extra == 'dev'
Requires-Dist: ruff>=0.1.0; extra == 'dev'
Provides-Extra: system-control
Requires-Dist: comtypes; extra == 'system-control'
Requires-Dist: pycaw; extra == 'system-control'
Requires-Dist: screen-brightness-control; extra == 'system-control'
